watchmap/__init__.py
watchmap/__main__.py
watchmap/templates/activity.html
watchmap/watchmap.py
watchmap-1.2.0.dist-info/LICENSE
watchmap-1.2.0.dist-info/METADATA
watchmap-1.2.0.dist-info/WHEEL
watchmap-1.2.0.dist-info/entry_points.txt
watchmap-1.2.0.dist-info/RECORD
