Metadata-Version: 2.1
Name: watchmap
Version: 1.2.0
Summary: Plots Activities (run, walk, swim, etc) from a Garmin device
License: GPL3
Author: nbr23
Author-email: max@23.tf
Requires-Python: >=3.6,<4.0
Classifier: License :: Other/Proprietary License
Classifier: Programming Language :: Python :: 3
Classifier: Programming Language :: Python :: 3.6
Classifier: Programming Language :: Python :: 3.7
Classifier: Programming Language :: Python :: 3.8
Classifier: Programming Language :: Python :: 3.9
Classifier: Programming Language :: Python :: 3.10
Classifier: Programming Language :: Python :: 3.11
Classifier: Programming Language :: Python :: 3.12
Requires-Dist: fitparse (>=1.2.0,<2.0.0)
Requires-Dist: folium (>=0.14.0,<0.15.0)
Requires-Dist: matplotlib (>=3.7.5,<4.0.0)
Requires-Dist: pandas (>=2.0.3,<3.0.0)
Requires-Dist: plotly (>=5.17.0,<6.0.0)
